pycryptodo/__init__.py
pycryptodo/math.py
pycryptodo/piico/__init__.py
pycryptodo/piico/cipher.py
pycryptodo/piico/device.py
pycryptodo/piico/digest.py
pycryptodo/piico/ecc.py
pycryptodo/piico/exception.py
pycryptodo/piico/session.py
pycryptodo/piico/session_mixin.py
pycryptodo-3.21.1.dist-info/LICENSE
pycryptodo-3.21.1.dist-info/METADATA
pycryptodo-3.21.1.dist-info/WHEEL
pycryptodo-3.21.1.dist-info/top_level.txt
pycryptodo-3.21.1.dist-info/RECORD
